tls_session/__init__.py
tls_session/fingerprints.py
tls_session/session.py
tls_xession-1.0.1.dist-info/METADATA
tls_xession-1.0.1.dist-info/WHEEL
tls_xession-1.0.1.dist-info/top_level.txt
tls_xession-1.0.1.dist-info/RECORD
