Metadata-Version: 2.4
Name: tls_xession
Version: 1.0.1
Summary: TLS fingerprinted HTTP client replacement for requests.Session
Author-email: Md Josif Khan <josifkhn@gmail.com>
License: MIT
Keywords: tls,tls client,tls_session,tls request,tls http client,http2
Classifier: Programming Language :: Python :: 3
Classifier: License :: OSI Approved :: MIT License
Classifier: Operating System :: OS Independent
Requires-Python: >=3.7
